tracex/__init__.py
tracex/engine.py
tracex/graph.py
tracex-0.1.0.dist-info/LICENSE
tracex-0.1.0.dist-info/METADATA
tracex-0.1.0.dist-info/WHEEL
tracex-0.1.0.dist-info/top_level.txt
tracex-0.1.0.dist-info/RECORD
