Metadata-Version: 2.1
Name: tracex
Version: 0.1.0
Summary: tracex: tracing / visualization
Home-page: https://github.com/rishiraj/tracex
Author: Rishiraj Acharya
Author-email: heyrishiraj@gmail.com
License: Apache 2.0
Platform: linux
Platform: unix
Requires-Python: >=3.6
License-File: LICENSE
Requires-Dist: graphviz (==0.10.1)
